pyburn_build/__init__.py
pyburn_build/__main__.py
pyburn_build/builders/build_manager.py
pyburn_build/builders/builders.py
pyburn_build/cache.py
pyburn_build/config/base.py
pyburn_build/config/configsaver.py
pyburn_build/config/project_config.py
pyburn_build/config/toolchain_config.py
pyburn_build/creator.py
pyburn_build/exceptions.py
pyburn_build/features/templates.py
pyburn_build/templates.py
pyburn_build/utils.py
pyburn_build-0.3.7.dist-info/LICENSE
pyburn_build-0.3.7.dist-info/METADATA
pyburn_build-0.3.7.dist-info/WHEEL
pyburn_build-0.3.7.dist-info/entry_points.txt
pyburn_build-0.3.7.dist-info/RECORD
