Metadata-Version: 2.1
Name: pyburn-build
Version: 0.3.7
Summary: build system written in python for projects in C and C++
License: GNU LGPL v2.1
Author: alexeev-prog
Author-email: alexeev.dev@mail.ru
Requires-Python: >=3.10,<4.0
Classifier: License :: Other/Proprietary License
Classifier: Programming Language :: Python :: 3
Classifier: Programming Language :: Python :: 3.10
Classifier: Programming Language :: Python :: 3.11
Classifier: Programming Language :: Python :: 3.12
Requires-Dist: PyYAML (>=6.0.2,<7.0.0)
Requires-Dist: click (>=8.1.7,<9.0.0)
Requires-Dist: configparser (>=7.1.0,<8.0.0)
Requires-Dist: loguru (>=0.7.2,<0.8.0)
Requires-Dist: requests (>=2.32.3,<3.0.0)
Requires-Dist: rich (>=13.9.4,<14.0.0)
Requires-Dist: toml (>=0.10.2,<0.11.0)
